{
    "spleen": 1,
    "kidney_right": 2,
    "kidney_left": 2,
    "gallbladder": 3,
    "liver": 4,
    "stomach": 5,
    "aorta": 6,
    "inferior_vena_cava": 6,
    "portal_vein_and_splenic_vein": 6,
    "pancreas": 7,
    "adrenal_gland_right": 8,
    "adrenal_gland_left": 8,
    "lung_upper_lobe_left": 9,
    "lung_lower_lobe_left": 9,
    "lung_upper_lobe_right": 9,
    "lung_middle_lobe_right": 9,
    "lung_lower_lobe_right": 9,
    "vertebrae_L5": 10,
    "vertebrae_L4": 10,
    "vertebrae_L3": 10,
    "vertebrae_L2": 10,
    "vertebrae_L1": 10,
    "vertebrae_T12": 10,
    "vertebrae_T11": 10,
    "vertebrae_T10": 10,
    "vertebrae_T9": 10,
    "vertebrae_T8": 10,
    "vertebrae_T7": 10,
    "vertebrae_T6": 10,
    "vertebrae_T5": 10,
    "vertebrae_T4": 10,
    "vertebrae_T3": 10,
    "vertebrae_T2": 10,
    "vertebrae_T1": 10,
    "vertebrae_C7": 10,
    "vertebrae_C6": 10,
    "vertebrae_C5": 10,
    "vertebrae_C4": 10,
    "vertebrae_C3": 10,
    "vertebrae_C2": 10,
    "vertebrae_C1": 10,
    "esophagus": 5,
    "trachea": 5,
    "heart_myocardium": 11,
    "heart_atrium_left": 11,
    "heart_ventricle_left": 11,
    "heart_atrium_right": 11,
    "heart_ventricle_right": 11,
    "pulmonary_artery": 6,
    "brain": 12,
    "iliac_artery_left": 6,
    "iliac_artery_right": 6,
    "iliac_vena_left": 6,
    "iliac_vena_right": 6,
    "small_bowel": 5,
    "duodenum": 5,
    "colon": 5,
    "rib_left_1": 10,
    "rib_left_2": 10,
    "rib_left_3": 10,
    "rib_left_4": 10,
    "rib_left_5": 10,
    "rib_left_6": 10,
    "rib_left_7": 10,
    "rib_left_8": 10,
    "rib_left_9": 10,
    "rib_left_10": 10,
    "rib_left_11": 10,
    "rib_left_12": 10,
    "rib_right_1": 10,
    "rib_right_2": 10,
    "rib_right_3": 10,
    "rib_right_4": 10,
    "rib_right_5": 10,
    "rib_right_6": 10,
    "rib_right_7": 10,
    "rib_right_8": 10,
    "rib_right_9": 10,
    "rib_right_10": 10,
    "rib_right_11": 10,
    "rib_right_12": 10,
    "humerus_left": 10,
    "humerus_right": 10,
    "scapula_left": 10,
    "scapula_right": 10,
    "clavicula_left": 10,
    "clavicula_right": 10,
    "femur_left": 10,
    "femur_right": 10,
    "hip_left": 10,
    "hip_right": 10,
    "sacrum": 10,
    "face": 13,
    "gluteus_maximus_left": 14,
    "gluteus_maximus_right": 14,
    "gluteus_medius_left": 14,
    "gluteus_medius_right": 14,
    "gluteus_minimus_left": 14,
    "gluteus_minimus_right": 14,
    "autochthon_left": 14,
    "autochthon_right": 14,
    "iliopsoas_left": 14,
    "iliopsoas_right": 14,
    "urinary_bladder": 15
}